ttun/__init__.py
ttun/__main__.py
ttun/client.py
ttun/inspect_server.py
ttun/pubsub.py
ttun/settings.py
ttun/types.py
ttun/staticfiles/index.html
ttun/staticfiles/assets/index-BPO8aseg.js
ttun/staticfiles/assets/index-ClgW4qw_.css
ttun-2.2.0.dist-info/licenses/LICENSE
ttun-2.2.0.dist-info/METADATA
ttun-2.2.0.dist-info/WHEEL
ttun-2.2.0.dist-info/entry_points.txt
ttun-2.2.0.dist-info/top_level.txt
ttun-2.2.0.dist-info/RECORD
