Metadata-Version: 2.4
Name: ttun
Version: 2.2.0
Summary: Expose a local port via your selfhosted TTUN Server
Author: Tom van der Lee
License: BSD-3-Clause
License-File: LICENSE
Requires-Dist: websockets~=10.0
Requires-Dist: aiohttp[speedups]~=3.8
Requires-Dist: appdirs~=1.4
Dynamic: license-file
